setup.py
netease/__init__.py
netease/main.py
wise_dl.egg-info/PKG-INFO
wise_dl.egg-info/SOURCES.txt
wise_dl.egg-info/dependency_links.txt
wise_dl.egg-info/entry_points.txt
wise_dl.egg-info/requires.txt
wise_dl.egg-info/top_level.txt