Metadata-Version: 1.0
Name: wise-dl
Version: 0.4
Summary: 网易云音乐歌曲下载器
Home-page: http://hfut.oyj.cn
Author: wise
Author-email: wisecsj@gmail.com
License: UNKNOWN
Keywords: music,netease,download,command tool
Platform: UNKNOWN
